cnvrgv2/__init__.py
cnvrgv2/_version.py
cnvrgv2/async.py
cnvrgv2/cnvrg.py
cnvrgv2/context.py
cnvrgv2/errors.py
cnvrgv2/proxy.py
cnvrgv2/cli/__init__.py
cnvrgv2/cli/cli.py
cnvrgv2/cli/logger/__init__.py
cnvrgv2/cli/logger/logger.py
cnvrgv2/cli/modules/__init__.py
cnvrgv2/cli/modules/config/__init__.py
cnvrgv2/cli/modules/config/config.py
cnvrgv2/cli/modules/dataset/__init__.py
cnvrgv2/cli/modules/dataset/dataset.py
cnvrgv2/cli/modules/datasource/__init__.py
cnvrgv2/cli/modules/datasource/datasource.py
cnvrgv2/cli/modules/images/__init__.py
cnvrgv2/cli/modules/images/images.py
cnvrgv2/cli/modules/labels/__init__.py
cnvrgv2/cli/modules/labels/labels.py
cnvrgv2/cli/modules/libraries/__init__.py
cnvrgv2/cli/modules/libraries/library.py
cnvrgv2/cli/modules/logs/__init__.py
cnvrgv2/cli/modules/logs/logs.py
cnvrgv2/cli/modules/members/__init__.py
cnvrgv2/cli/modules/members/members.py
cnvrgv2/cli/modules/organization_settings/__init__.py
cnvrgv2/cli/modules/organization_settings/organization_settings.py
cnvrgv2/cli/modules/project/__init__.py
cnvrgv2/cli/modules/project/endpoint.py
cnvrgv2/cli/modules/project/experiment.py
cnvrgv2/cli/modules/project/flows.py
cnvrgv2/cli/modules/project/project.py
cnvrgv2/cli/modules/project/webapp.py
cnvrgv2/cli/modules/project/workspace.py
cnvrgv2/cli/modules/registries/__init__.py
cnvrgv2/cli/modules/registries/registries.py
cnvrgv2/cli/modules/ssh/__init__.py
cnvrgv2/cli/modules/ssh/ssh.py
cnvrgv2/cli/modules/storage_class/__init__.py
cnvrgv2/cli/modules/storage_class/storage_class.py
cnvrgv2/cli/modules/users/__init__.py
cnvrgv2/cli/modules/users/users.py
cnvrgv2/cli/modules/volumes/__init__.py
cnvrgv2/cli/modules/volumes/volume.py
cnvrgv2/cli/utils/__init__.py
cnvrgv2/cli/utils/decorators.py
cnvrgv2/cli/utils/dict_param.py
cnvrgv2/cli/utils/helpers.py
cnvrgv2/cli/utils/messages.py
cnvrgv2/cli/utils/options.py
cnvrgv2/cli/utils/progress_bar_utils.py
cnvrgv2/cli/utils/validators.py
cnvrgv2/config/__init__.py
cnvrgv2/config/config.py
cnvrgv2-1.1.8.dist-info/METADATA
cnvrgv2-1.1.8.dist-info/WHEEL
cnvrgv2-1.1.8.dist-info/entry_points.txt
cnvrgv2-1.1.8.dist-info/top_level.txt
cnvrgv2-1.1.8.dist-info/RECORD
